yaleclient/__init__.py
yaleclient/__main__.py
yaleclient/alarm.py
yaleclient/auth.py
yaleclient/cli.py
yaleclient/client.py
yaleclient/lock.py
yaleclient-0.2.2.dist-info/LICENSE
yaleclient-0.2.2.dist-info/METADATA
yaleclient-0.2.2.dist-info/WHEEL
yaleclient-0.2.2.dist-info/entry_points.txt
yaleclient-0.2.2.dist-info/top_level.txt
yaleclient-0.2.2.dist-info/RECORD
