Metadata-Version: 2.1
Name: yaleclient
Version: 0.2.2
Summary: Interact with Yale systems
Home-page: https://github.com/anderselton/yale-client
Author: Anders Elton
License: Apache 2.0
Download-URL: https://github.com/anderselton/yale-client
Keywords: alarm,Yale,Smart Alarm,Lock,doorman
Platform: UNKNOWN
Classifier: Programming Language :: Python :: 3
Classifier: License :: OSI Approved :: Apache Software License
Classifier: Operating System :: OS Independent
Requires-Dist: requests (>=2.0.0)
Requires-Dist: backoff (>=1.10.0)
